TATi/__init__.py
TATi/common.py
TATi/model.py
TATi/simulation.py
TATi/version.py
TATi/analysis/__init__.py
TATi/analysis/analyser_modules.py
TATi/analysis/averageenergieswriter.py
TATi/analysis/averagetrajectorywriter.py
TATi/analysis/covariance.py
TATi/analysis/covariance_perwalker.py
TATi/analysis/diffusionmap.py
TATi/analysis/freeenergy.py
TATi/analysis/integratedautocorrelation.py
TATi/analysis/integratedautocorrelation_perwalker.py
TATi/analysis/parsedrunfile.py
TATi/analysis/parsedtrajectory.py
TATi/datasets/__init__.py
TATi/datasets/classificationdatasets.py
TATi/diffusion_maps/__init__.py
TATi/diffusion_maps/diffusionmap.py
TATi/exploration/__init__.py
TATi/exploration/explorer.py
TATi/exploration/get_executables.py
TATi/exploration/trajectorydata.py
TATi/exploration/trajectorydatacontainer.py
TATi/exploration/trajectoryjob.py
TATi/exploration/trajectoryjob_analyze.py
TATi/exploration/trajectoryjob_check_gradient.py
TATi/exploration/trajectoryjob_extract_minimum_candidates.py
TATi/exploration/trajectoryjob_prune.py
TATi/exploration/trajectoryjob_sample.py
TATi/exploration/trajectoryjob_train.py
TATi/exploration/trajectoryjobid.py
TATi/exploration/trajectoryjobqueue.py
TATi/exploration/trajectoryprocess.py
TATi/exploration/trajectoryprocess_sample.py
TATi/exploration/trajectoryprocess_train.py
TATi/exploration/trajectoryprocessqueue.py
TATi/exploration/trajectoryqueue.py
TATi/models/__init__.py
TATi/models/basetype.py
TATi/models/evaluationcache.py
TATi/models/helpers.py
TATi/models/modelstate.py
TATi/models/accumulators/__init__.py
TATi/models/accumulators/accumulated_values.py
TATi/models/accumulators/accumulator.py
TATi/models/accumulators/averagesaccumulator.py
TATi/models/accumulators/runinfoaccumulator.py
TATi/models/accumulators/trajectoryaccumulator.py
TATi/models/input/__init__.py
TATi/models/input/datasetpipeline.py
TATi/models/input/inmemorypipeline.py
TATi/models/input/inputpipeline.py
tati-0.9.5.dist-info/METADATA
tati-0.9.5.dist-info/RECORD
tati-0.9.5.dist-info/WHEEL
tati-0.9.5.dist-info/entry_points.txt
tati-0.9.5.dist-info/top_level.txt
