Metadata-Version: 2.1
Name: tati
Version: 0.9.5
Summary: ThermodynamicAnalyticsToolkit - analyze loss manifolds of neural networks
Home-page: https://github.com/alan-turing-institute/ThermodynamicAnalyticsToolkit
Author: TATi Team
Maintainer: Frederik Heber
Maintainer-email: frederik.heber@gmail.com
License: GPL-3
Project-URL: Documentation, https://thermodynamicanalyticstoolkit.github.io/
Project-URL: Source Code, https://github.com/alan-turing-institute/ThermodynamicAnalyticsToolkit/tree
Project-URL: Bug Tracker, https://github.com/alan-turing-institute/ThermodynamicAnalyticsToolkit/issues
Platform: UNKNOWN
Classifier: Intended Audience :: Science/Research
Classifier: License :: OSI Approved :: GNU General Public License v3 (GPLv3)
Classifier: Operating System :: POSIX
Classifier: Programming Language :: Python :: 3
Classifier: Programming Language :: Python :: 3.4
Classifier: Programming Language :: Python :: 3.5
Classifier: Programming Language :: Python :: 3.6
Classifier: Topic :: Scientific/Engineering :: Artificial Intelligence
Classifier: Topic :: Scientific/Engineering :: Mathematics
Classifier: Topic :: Scientific/Engineering :: Physics
Provides-Extra: IAT
Requires-Dist: matplotlib
Requires-Dist: numpy (>=1.7)
Requires-Dist: pandas
Requires-Dist: scipy
Requires-Dist: scikit-learn
Requires-Dist: tensorflow (>=1.4.1)
Provides-Extra: IAT
Requires-Dist: acor; extra == 'IAT'
